vidcraft/__init__.py
vidcraft-0.1.0.dist-info/WHEEL
vidcraft-0.1.0.dist-info/entry_points.txt
vidcraft-0.1.0.dist-info/METADATA
vidcraft-0.1.0.dist-info/RECORD
