Metadata-Version: 2.3
Name: vidcraft
Version: 0.1.0
Summary: Use your ffmpeg for transcodes without having to remember all the nifty options and best values.
Author: siru
Author-email: siru <siru@codessh.de>
Requires-Python: >=3.14
